testNump/__init__.py
testNump/number.py
testNump/run.py
testNump/version.py
testNump-0.0.2.dist-info/DESCRIPTION.rst
testNump-0.0.2.dist-info/METADATA
testNump-0.0.2.dist-info/RECORD
testNump-0.0.2.dist-info/WHEEL
testNump-0.0.2.dist-info/metadata.json
testNump-0.0.2.dist-info/top_level.txt
