Metadata-Version: 2.0
Name: testNump
Version: 0.0.2
Summary: A test project
Home-page: https://github.com/alvinhui/
Author: Alvin Hui
Author-email: alvinxwt@gmail.com
License: MIT
Platform: UNKNOWN
Requires-Dist: numpy (>=1.13)
